discretize/unstructured_mesh.py
discretize/tree_mesh.py
discretize/curvilinear_mesh.py
discretize/tensor_cell.py
discretize/tensor_mesh.py
discretize/tests.py
discretize/__init__.py
discretize/View.py
discretize/cylindrical_mesh.py
discretize/_extensions/tree_ext.cpython-310-x86_64-linux-gnu.so
discretize/_extensions/__init__.py
discretize/_extensions/simplex_helpers.cpython-310-x86_64-linux-gnu.so
discretize/_extensions/interputils_cython.cpython-310-x86_64-linux-gnu.so
discretize/utils/interpolation_utils.py
discretize/utils/curvilinear_utils.py
discretize/utils/interputils.py
discretize/utils/mesh_utils.py
discretize/utils/curvutils.py
discretize/utils/codeutils.py
discretize/utils/matrix_utils.py
discretize/utils/coordutils.py
discretize/utils/io_utils.py
discretize/utils/__init__.py
discretize/utils/meshutils.py
discretize/utils/code_utils.py
discretize/utils/coordinate_utils.py
discretize/utils/matutils.py
discretize/operators/inner_products.py
discretize/operators/__init__.py
discretize/operators/differential_operators.py
discretize/Tests/__init__.py
discretize/base/base_tensor_mesh.py
discretize/base/__init__.py
discretize/base/base_mesh.py
discretize/base/base_regular_mesh.py
discretize/mixins/__init__.py
discretize/mixins/vtk_mod.py
discretize/mixins/mesh_io.py
discretize/mixins/omf_mod.py
discretize/mixins/mpl_mod.py
discretize-0.11.3.dist-info/RECORD
discretize-0.11.3.dist-info/METADATA
discretize-0.11.3.dist-info/WHEEL
discretize-0.11.3.dist-info/LICENSE
