Metadata-Version: 2.1
Name: discretize
Version: 0.11.3
Summary: Discretization tools for finite volume and inverse problems
Keywords: finite volume,discretization,pde,ode
Author-Email: SimPEG developers <rowanc1@gmail.com>
License: The MIT License (MIT)
Classifier: Development Status :: 4 - Beta
Classifier: Intended Audience :: Developers
Classifier: Intended Audience :: Science/Research
Classifier: License :: OSI Approved :: MIT License
Classifier: Programming Language :: Python
Classifier: Programming Language :: Cython
Classifier: Programming Language :: C++
Classifier: Topic :: Scientific/Engineering
Classifier: Topic :: Scientific/Engineering :: Mathematics
Classifier: Topic :: Scientific/Engineering :: Physics
Classifier: Operating System :: Microsoft :: Windows
Classifier: Operating System :: POSIX
Classifier: Operating System :: Unix
Classifier: Operating System :: MacOS
Classifier: Natural Language :: English
Project-URL: Homepage, https://simpeg.xyz
Project-URL: Documentation, https://discretize.simpeg.xyz
Project-URL: Repository, http://github.com/simpeg/discretize.git
Requires-Python: >=3.10
Requires-Dist: numpy>=1.22.4
Requires-Dist: scipy>=1.8
Provides-Extra: plot
Requires-Dist: matplotlib; extra == "plot"
Provides-Extra: viz
Requires-Dist: vtk>=6; extra == "viz"
Requires-Dist: pyvista; extra == "viz"
Provides-Extra: omf
Requires-Dist: omf; extra == "omf"
Provides-Extra: all
Requires-Dist: discretize[omf,plot,viz]; extra == "all"
Provides-Extra: doc
Requires-Dist: sphinx!=4.1.0; extra == "doc"
Requires-Dist: pydata-sphinx-theme==0.15.4; extra == "doc"
Requires-Dist: sphinx-gallery==0.1.13; extra == "doc"
Requires-Dist: numpydoc>=1.5; extra == "doc"
Requires-Dist: jupyter; extra == "doc"
Requires-Dist: graphviz; extra == "doc"
Requires-Dist: pillow; extra == "doc"
Requires-Dist: pooch; extra == "doc"
Requires-Dist: discretize[all]; extra == "doc"
Provides-Extra: test
Requires-Dist: pytest; extra == "test"
Requires-Dist: pytest-cov; extra == "test"
Requires-Dist: sympy; extra == "test"
Requires-Dist: discretize[all,doc]; extra == "test"
Provides-Extra: style
Requires-Dist: black==24.3.0; extra == "style"
Requires-Dist: flake8==7.0.0; extra == "style"
Requires-Dist: flake8-bugbear==23.12.2; extra == "style"
Requires-Dist: flake8-builtins==2.2.0; extra == "style"
Requires-Dist: flake8-mutable==1.2.0; extra == "style"
Requires-Dist: flake8-rst-docstrings==0.3.0; extra == "style"
Requires-Dist: flake8-docstrings==1.7.0; extra == "style"
Requires-Dist: flake8-pyproject==1.2.3; extra == "style"
Provides-Extra: build
Requires-Dist: meson-python>=0.14.0; extra == "build"
Requires-Dist: meson; extra == "build"
Requires-Dist: ninja; extra == "build"
Requires-Dist: numpy>=1.22.4; extra == "build"
Requires-Dist: cython>=0.29.35; extra == "build"
Requires-Dist: setuptools_scm; extra == "build"
